{
    "kb1": {
        "fire": [
            {
                "button": "M",
                "device": "kb",
                "id": 0
            }
        ],
        "down": [
            {
                "button": "Down",
                "device": "kb",
                "id": 0
            }
        ],
        "left": [
            {
                "button": "Left",
                "device": "kb",
                "id": 0
            }
        ],
        "right": [
            {
                "button": "Right",
                "device": "kb",
                "id": 0
            }
        ],
        "up": [
            {
                "button": "Up",
                "device": "kb",
                "id": 0
            }
        ]
    },
    "kb2": {
        "down": [
            {
                "button": "S",
                "device": "kb",
                "id": 0
            }
        ],
        "fire": [
            {
                "button": "1",
                "device": "kb",
                "id": 0
            }
        ],
        "left": [
            {
                "button": "A",
                "device": "kb",
                "id": 0
            }
        ],
        "right": [
            {
                "button": "D",
                "device": "kb",
                "id": 0
            }
        ],
        "up": [
            {
                "button": "W",
                "device": "kb",
                "id": 0
            }
        ]
    }
}